stackraise/__init__.py
stackraise/ai/__init__.py
stackraise/ai/rpa.py
stackraise/ai/toolset.py
stackraise/app.py
stackraise/auth/__init__.py
stackraise/auth/model.py
stackraise/auth/service.py
stackraise/ctrl/__init__.py
stackraise/ctrl/change_stream.py
stackraise/ctrl/crud_controller.py
stackraise/ctrl/file_storage.py
stackraise/db/__init__.py
stackraise/db/adapter.py
stackraise/db/collection.py
stackraise/db/cursor.py
stackraise/db/document.py
stackraise/db/exceptions.py
stackraise/db/id.py
stackraise/db/index.py
stackraise/db/persistence.py
stackraise/db/pipeline.py
stackraise/db/protocols.py
stackraise/di.py
stackraise/event.py
stackraise/inflection.py
stackraise/io/__init__.py
stackraise/io/imap_client.py
stackraise/io/smtp_client.py
stackraise/logging.py
stackraise/model/__init__.py
stackraise/model/core.py
stackraise/model/dto.py
stackraise/model/email_message.py
stackraise/model/file.py
stackraise/model/name_email.py
stackraise/model/query_filters.py
stackraise/model/time_range.py
stackraise/model/validation.py
stackraise/templating/__init__.py
stackraise/templating/exceptions.py
stackraise/templating/image/__init__.py
stackraise/templating/image/model.py
stackraise/templating/image/processor.py
stackraise/templating/parser.py
stackraise/templating/pptx/__init__.py
stackraise/templating/pptx/pptx_engine.py
stackraise/templating/pptx/slide_renderer.py
stackraise/templating/tracer.py
stackraise-0.1.4.dist-info/METADATA
stackraise-0.1.4.dist-info/WHEEL
stackraise-0.1.4.dist-info/RECORD
